hydroflows/__init__.py
hydroflows/_typing.py
hydroflows/config.py
hydroflows/events.py
hydroflows/log.py
hydroflows/cfg/__init__.py
hydroflows/cfg/fa_database_build.yml
hydroflows/cfg/fiat_build.yml
hydroflows/cfg/sfincs_build.yml
hydroflows/cfg/wflow_build.yml
hydroflows/cfg/infographics/config_charts.toml
hydroflows/cfg/infographics/config_risk_charts.toml
hydroflows/cfg/infographics/config_roads.toml
hydroflows/cfg/infographics/images/car.png
hydroflows/cfg/infographics/images/cart.png
hydroflows/cfg/infographics/images/factory.png
hydroflows/cfg/infographics/images/house.png
hydroflows/cfg/infographics/images/info.png
hydroflows/cfg/infographics/images/money.png
hydroflows/cfg/infographics/images/truck.png
hydroflows/cfg/infometrics/metrics_config.toml
hydroflows/cli/__init__.py
hydroflows/cli/main.py
hydroflows/methods/__init__.py
hydroflows/methods/catalog/__init__.py
hydroflows/methods/catalog/merge_catalogs.py
hydroflows/methods/climate/__init__.py
hydroflows/methods/climate/change_factor.py
hydroflows/methods/climate/climatology.py
hydroflows/methods/climate/grid_utils.py
hydroflows/methods/climate/meteo.py
hydroflows/methods/climate/utils.py
hydroflows/methods/coastal/__init__.py
hydroflows/methods/coastal/coastal_design_events.py
hydroflows/methods/coastal/coastal_design_events_from_rp_data.py
hydroflows/methods/coastal/coastal_tidal_analysis.py
hydroflows/methods/coastal/coastal_utils.py
hydroflows/methods/coastal/future_slr.py
hydroflows/methods/coastal/get_coast_rp.py
hydroflows/methods/coastal/get_gtsm_data.py
hydroflows/methods/discharge/__init__.py
hydroflows/methods/discharge/fluvial_design_events.py
hydroflows/methods/dummy/__init__.py
hydroflows/methods/dummy/combine_dummy_events.py
hydroflows/methods/dummy/postprocess_dummy_event.py
hydroflows/methods/dummy/prepare_dummy_events.py
hydroflows/methods/dummy/run_dummy_event.py
hydroflows/methods/fiat/__init__.py
hydroflows/methods/fiat/fiat_build.py
hydroflows/methods/fiat/fiat_run.py
hydroflows-0.1.0.dist-info/entry_points.txt
hydroflows-0.1.0.dist-info/licenses/LICENSE
hydroflows-0.1.0.dist-info/WHEEL
hydroflows-0.1.0.dist-info/METADATA
hydroflows-0.1.0.dist-info/RECORD
