Metadata-Version: 2.4
Name: hydroflows
Version: 0.1.0
Summary: HydroFlows: Automated and reproducible hydro model workflows.
Author-email: Dirk Eilander <dirk.eilander@deltares.nl>, Willem Tromp <willem.tromp@deltares.nl>, Athanasios Tsiokanos <athanasios.tsiokanos@deltares.nl>, Brendan Dalmijn <info@deltares.nl>, Sarah Rautenbach <info@deltares.nl>
Requires-Python: >=3.10
Classifier: Development Status :: 5 - Production/Stable
Classifier: Intended Audience :: Developers
Classifier: Intended Audience :: Science/Research
Classifier: Topic :: Scientific/Engineering :: Hydrology
Classifier: License :: OSI Approved :: MIT License
Classifier: Programming Language :: Python :: 3
License-File: LICENSE
Requires-Dist: click
Requires-Dist: geopandas>=1.0, <2.0
Requires-Dist: graphviz
Requires-Dist: importlib-metadata
Requires-Dist: jinja2
Requires-Dist: pandas
Requires-Dist: pooch
Requires-Dist: pydantic>=2.9, <3
Requires-Dist: pyyaml
Requires-Dist: typing_extensions
Requires-Dist: tqdm
Requires-Dist: pip>=23.1.2 ; extra == "dev"
Requires-Dist: pre-commit ; extra == "dev"
Requires-Dist: ruff ; extra == "dev"
Requires-Dist: tomli ; extra == "dev"
Requires-Dist: hydroflows[doc, extra, methods, test] ; extra == "dev"
Requires-Dist: nbsphinx ; extra == "doc"
Requires-Dist: pip>=23.1.2 ; extra == "doc"
Requires-Dist: sphinx ; extra == "doc"
Requires-Dist: sphinx_design ; extra == "doc"
Requires-Dist: pydata-sphinx-theme ; extra == "doc"
Requires-Dist: autodoc_pydantic ; extra == "doc"
Requires-Dist: sphinxcontrib-programoutput ; extra == "doc"
Requires-Dist: hydroflows[extra, methods] ; extra == "doc"
Requires-Dist: papermill ; extra == "extra"
Requires-Dist: jupyter ; extra == "extra"
Requires-Dist: snakemake>=8.20, <9.0 ; extra == "extra"
Requires-Dist: hydroflows[dev, doc, test, extra, methods, models] ; extra == "full"
Requires-Dist: cartopy ; extra == "methods"
Requires-Dist: contextily ; extra == "methods"
Requires-Dist: dask==2024.11.2 ; extra == "methods"
Requires-Dist: fiat-toolbox>=0.1.16 ; extra == "methods"
Requires-Dist: hatyan>=2.9, <3.0 ; extra == "methods"
Requires-Dist: hydromt>=0.9.4, <1.0 ; extra == "methods"
Requires-Dist: hydromt-fiat>=0.5.4, <1.0 ; extra == "methods"
Requires-Dist: hydromt_sfincs>=1.1.0, <2.0 ; extra == "methods"
Requires-Dist: hydromt_wflow>=0.6, <1.0 ; extra == "methods"
Requires-Dist: matplotlib ; extra == "methods"
Requires-Dist: netcdf4 ; extra == "methods"
Requires-Dist: numpy>=1.20 ; extra == "methods"
Requires-Dist: requests ; extra == "methods"
Requires-Dist: shapely ; extra == "methods"
Requires-Dist: xarray==2024.3.0 ; extra == "methods"
Requires-Dist: delft_fiat==0.2.0 ; extra == "models"
Requires-Dist: juliaup ; extra == "models"
Requires-Dist: pytest>=2.7.3 ; extra == "test"
Requires-Dist: pytest-cov ; extra == "test"
Requires-Dist: pytest-mock ; extra == "test"
Requires-Dist: pytest-timeout ; extra == "test"
Project-URL: Documentation, https://deltares-research.github.io/HydroFlows
Project-URL: Source, https://github.com/Deltares-research/HydroFlows
Provides-Extra: dev
Provides-Extra: doc
Provides-Extra: extra
Provides-Extra: full
Provides-Extra: methods
Provides-Extra: models
Provides-Extra: test
